curvanato/__init__.py
curvanato/curvature.py
curvanato/data/caud_vent.nii.gz
curvanato/data/labeled_caudate_head_mid_tail.nii.gz
curvanato/data/labeled_caudate_medial_vs_lateral.nii.gz
curvanato-1.2.0.dist-info/LICENSE
curvanato-1.2.0.dist-info/METADATA
curvanato-1.2.0.dist-info/WHEEL
curvanato-1.2.0.dist-info/top_level.txt
curvanato-1.2.0.dist-info/RECORD
