Metadata-Version: 2.2
Name: curvanato
Version: 1.2.0
Summary: Anatomical curvature processing for medical images.
Author: Dorian Pustina
Author-email: "Brian B. Avants" <stnava@gmail.com>
Project-URL: homepage, https://github.com/stnava/curvanato
Keywords: curvanato,caudate,medical image processing
Classifier: Programming Language :: Python :: 3
Classifier: Operating System :: OS Independent
License-File: LICENSE
Requires-Dist: numpy
Requires-Dist: antspyx>=0.4.2
Requires-Dist: antspynet
Requires-Dist: antspyt1w>=0.9.4
Requires-Dist: antspymm
Requires-Dist: scikit-learn
Requires-Dist: requests
Requires-Dist: statsmodels
Requires-Dist: matplotlib
